README.txt
setup.cfg
setup.py
cityhall/__init__.py
cityhall/errors.py
cityhall.egg-info/PKG-INFO
cityhall.egg-info/SOURCES.txt
cityhall.egg-info/dependency_links.txt
cityhall.egg-info/requires.txt
cityhall.egg-info/top_level.txt
test/test_auth.py
test/test_env.py