Metadata-Version: 1.1
Name: cityhall
Version: 0.0.11
Summary: A library for accessing City Hall Setting Server
Home-page: https://github.com/f00f-nyc/cityhall-python
Author: Alex Popa
Author-email: alex.popa@digitalborderlands.com
License: AGPL
Download-URL: https://codeload.github.com/f00f-nyc/cityhall-python/legacy.tar.gz/v0.0.11
Keywords: cityhall,enterprise settings,settings,settings server,cityhall,City Hall
Platform: UNKNOWN
